MANIFEST.in
setup.py
django_sendgrid.egg-info/PKG-INFO
django_sendgrid.egg-info/SOURCES.txt
django_sendgrid.egg-info/dependency_links.txt
django_sendgrid.egg-info/top_level.txt
example_project/main/__init__.py
example_project/main/forms.py
example_project/main/models.py
example_project/main/tests.py
example_project/main/urls.py
example_project/main/views.py
example_project/sendgrid/__init__.py
example_project/sendgrid/admin.py
example_project/sendgrid/backends.py
example_project/sendgrid/constants.py
example_project/sendgrid/header.py
example_project/sendgrid/mail.py
example_project/sendgrid/message.py
example_project/sendgrid/mixins.py
example_project/sendgrid/models.py
example_project/sendgrid/signals.py
example_project/sendgrid/tasks.py
example_project/sendgrid/tests.py
example_project/sendgrid/urls.py
example_project/sendgrid/views.py
example_project/sendgrid/migrations/0001_initial.py
example_project/sendgrid/migrations/0002_auto__chg_field_emailmessage_to_email__chg_field_emailmessage_from_ema.py
example_project/sendgrid/migrations/0003_auto__add_category.py
example_project/sendgrid/migrations/0004_auto__add_uniqueargument__add_argument.py
example_project/sendgrid/migrations/0005_auto__add_eventtype__add_event.py
example_project/sendgrid/migrations/__init__.py
example_project/sendgrid/utils/__init__.py
example_project/sendgrid/utils/filterutils.py
example_project/sendgrid/utils/requestfactory.py
sendgrid/__init__.py
sendgrid/admin.py
sendgrid/backends.py
sendgrid/constants.py
sendgrid/header.py
sendgrid/mail.py
sendgrid/message.py
sendgrid/mixins.py
sendgrid/models.py
sendgrid/signals.py
sendgrid/tasks.py
sendgrid/tests.py
sendgrid/urls.py
sendgrid/views.py
sendgrid/fixtures/initial_data.json
sendgrid/migrations/0001_initial.py
sendgrid/migrations/0002_auto__chg_field_emailmessage_to_email__chg_field_emailmessage_from_ema.py
sendgrid/migrations/0003_auto__add_category.py
sendgrid/migrations/0004_auto__add_uniqueargument__add_argument.py
sendgrid/migrations/0005_auto__add_eventtype__add_event.py
sendgrid/migrations/__init__.py
sendgrid/utils/__init__.py
sendgrid/utils/filterutils.py
