Metadata-Version: 1.0
Name: django-sendgrid
Version: 1.0.1
Summary: django-sendgrid
Home-page: http://ryanbalfanz.github.com/django-sendgrid/
Author: Ryan Balfanz
Author-email: ryan@ryanbalfanz.net
License: UNKNOWN
Platform: any
